duckduckgo_mcp_server/__init__.py
duckduckgo_mcp_server/server.py
duckduckgo_mcp_server_ssl_fix-0.2.0.dist-info/METADATA
duckduckgo_mcp_server_ssl_fix-0.2.0.dist-info/WHEEL
duckduckgo_mcp_server_ssl_fix-0.2.0.dist-info/entry_points.txt
duckduckgo_mcp_server_ssl_fix-0.2.0.dist-info/licenses/LICENSE
duckduckgo_mcp_server_ssl_fix-0.2.0.dist-info/RECORD
